{
  "name": "burninghearthrun",
  "palette_bg": [30, 20, 15],
  "tile_size": 32,
  "width_tiles": 30,
  "height_tiles": 17,
  "route": [
    [3, 1],
    [4, 1],
    [5, 1],
    [6, 2],
    [7, 2],
    [8, 2],
    [9, 2],
    [10, 2],
    [11, 2],
    [12, 2],
    [13, 3],
    [14, 3],
    [15, 3],
    [16, 3],
    [17, 3],
    [18, 3],
    [19, 3],
    [20, 3],
    [21, 4],
    [22, 4],
    [23, 4],
    [24, 4],
    [25, 4]
  ],
  "hero_step_interval_s": 0.22,
  "objects": [
    { "kind": "floor", "sprite": "Normal_Grass_32x32", "x": 0, "y": 0, "w_tiles": 6, "h_tiles": 1 },

    { "kind": "floor", "sprite": "Dirt_32x32", "x": 6, "y": 0, "w_tiles": 7, "h_tiles": 1 },
    { "kind": "floor", "sprite": "Normal_Grass_32x32", "x": 6, "y": 1, "w_tiles": 7, "h_tiles": 1 },

    { "kind": "floor", "sprite": "Dirt_32x32", "x": 13, "y": 0, "w_tiles": 8, "h_tiles": 2 },
    { "kind": "floor", "sprite": "Normal_Grass_32x32", "x": 13, "y": 2, "w_tiles": 8, "h_tiles": 1 },

    { "kind": "floor", "sprite": "Dirt_32x32", "x": 21, "y": 0, "w_tiles": 9, "h_tiles": 3 },
    { "kind": "floor", "sprite": "Normal_Grass_32x32", "x": 21, "y": 3, "w_tiles": 9, "h_tiles": 1 },

    { "kind": "player_spawn", "sprite": "Peasant", "x": 0, "y": 1 },
    { "kind": "hero_spawn", "sprite": "Hero", "x": 3, "y": 1 },
    { "kind": "enemy_spawn", "sprite": "Enemy", "x": 3, "y": 1 },
    { "kind": "exit_spawn", "sprite": "", "x": 23, "y": 4 },

    { "kind": "house", "sprite": "House_Normal_96x96", "destroyed_sprite": "House_Destroyed_96x96", "x": 24, "y": 4, "w_tiles": 3, "h_tiles": 3 },

    { "kind": "fire_spawn", "sprite": "Fire_24x24", "x": 8, "y": 2 },
    { "kind": "fire_spawn", "sprite": "Fire_24x24", "x": 9, "y": 2 },
    { "kind": "fire_spawn", "sprite": "Fire_24x24", "x": 10, "y": 2 },

    { "kind": "fire_spawn", "sprite": "Fire_24x24", "x": 14, "y": 3 },
    { "kind": "fire_spawn", "sprite": "Fire_24x24", "x": 15, "y": 3 },

    { "kind": "fire_spawn", "sprite": "Fire_24x24", "x": 18, "y": 3 },
    { "kind": "fire_spawn", "sprite": "Fire_24x24", "x": 19, "y": 3 }
  ]
}

